sbmlutils/__init__.py
sbmlutils/biomodels.py
sbmlutils/console.py
sbmlutils/cytoscape.py
sbmlutils/equation.py
sbmlutils/factory.py
sbmlutils/log.py
sbmlutils/notes.py
sbmlutils/utils.py
sbmlutils/validation.py
sbmlutils/comp/__init__.py
sbmlutils/comp/comp.py
sbmlutils/comp/flatten.py
sbmlutils/converters/__init__.py
sbmlutils/converters/copasi.py
sbmlutils/converters/mathml.py
sbmlutils/converters/odefac.py
sbmlutils/converters/xpp.py
sbmlutils/converters/xpp_examples.py
sbmlutils/converters/xpp_helpers.py
sbmlutils/distrib/__init__.py
sbmlutils/distrib/distrib_examples.py
sbmlutils/distrib/distrib_packages.py
sbmlutils/examples/__init__.py
sbmlutils/examples/amount_species.py
sbmlutils/examples/annotation.py
sbmlutils/examples/assignment.py
sbmlutils/examples/boundary_condition.py
sbmlutils/examples/compartment_species_reaction.py
sbmlutils/examples/complete_model.py
sbmlutils/examples/distrib_comp.py
sbmlutils/examples/distrib_distributions.py
sbmlutils/examples/distrib_uncertainties.py
sbmlutils/examples/fbc_example.py
sbmlutils/examples/fbc_mass_charge.py
sbmlutils/examples/linear_chain.py
sbmlutils/examples/minimal_model.py
sbmlutils/examples/minimal_model_annotations.py
sbmlutils/examples/minimal_model_comp.py
sbmlutils/examples/model_composition.py
sbmlutils/examples/model_definitions.py
sbmlutils/examples/multiple_substance_units.py
sbmlutils/examples/nan.py
sbmlutils/examples/notes.py
sbmlutils/examples/random_network.py
sbmlutils/examples/reaction.py
sbmlutils/examples/simple_reaction_with_units.py
sbmlutils/examples/templates.py
sbmlutils/examples/unit_definitions.py
sbmlutils/examples/units_namespace.py
sbmlutils/examples/combine_archive/__init__.py
sbmlutils/examples/combine_archive/omex_models.py
sbmlutils/examples/dallaman/__init__.py
sbmlutils/examples/dallaman/factory.py
sbmlutils/examples/dallaman/model.py
sbmlutils/examples/demo/__init__.py
sbmlutils/examples/demo/demo_annotations.xlsx
sbmlutils/examples/demo/factory.py
sbmlutils-0.7.6.dist-info/LICENSE
sbmlutils-0.7.6.dist-info/METADATA
sbmlutils-0.7.6.dist-info/WHEEL
sbmlutils-0.7.6.dist-info/top_level.txt
sbmlutils-0.7.6.dist-info/zip-safe
sbmlutils-0.7.6.dist-info/RECORD
