Metadata-Version: 2.1
Name: sbmlutils
Version: 0.7.6
Summary: sbmlutils are utilities for working with SBML.
Home-page: https://github.com/matthiaskoenig/sbmlutils
Download-URL: https://pypi.org/project/sbmlutils
Author: Matthias Koenig
Author-email: konigmatt@googlemail.com
Maintainer: Matthias Koenig
Maintainer-email: konigmatt@googlemail.com
License: LGPL-3.0
Project-URL: Source Code, https://github.com/matthiaskoenig/sbmlutils
Project-URL: Documentation, https://sbmlutils.readthedocs.io
Project-URL: Bug Tracker, https://github.com/matthiaskoenig/sbmlutils/issues
Keywords: modeling,standardization,SBML
Classifier: Development Status :: 5 - Production/Stable
Classifier: Intended Audience :: Science/Research
Classifier: License :: OSI Approved :: GNU Lesser General Public License v3 (LGPLv3)
Classifier: Operating System :: OS Independent
Classifier: Programming Language :: Python :: 3.8
Classifier: Programming Language :: Python :: 3.9
Classifier: Programming Language :: Python :: 3.10
Classifier: Programming Language :: Python :: Implementation :: CPython
Classifier: Topic :: Scientific/Engineering
Classifier: Topic :: Scientific/Engineering :: Bio-Informatics
Requires-Python: >=3.8
License-File: LICENSE
Requires-Dist: pymetadata (>=0.3.0)
Requires-Dist: depinfo
Requires-Dist: rich
Requires-Dist: lxml
Requires-Dist: requests
Requires-Dist: jinja2
Requires-Dist: xmltodict
Requires-Dist: numpy (>=1.21.1)
Requires-Dist: python-libsbml (>=5.19.5)
Requires-Dist: scipy (>=1.8)
Requires-Dist: pandas (>=1.4)
Requires-Dist: pint (>=0.18)
Requires-Dist: tabulate (>=0.8.9)
Requires-Dist: beautifulsoup4 (>=4.10)
Requires-Dist: markdown-it-py (>=2.0.1)
Requires-Dist: openpyxl (>=3.0.9)
Requires-Dist: xmlschema (>=1.9.2)
Requires-Dist: matplotlib (>=3.5)
Requires-Dist: fastapi (>=0.73.0)
Requires-Dist: uvicorn (>=0.14.4)
Requires-Dist: python-multipart (>=0.0.5)
Requires-Dist: py2cytoscape (>=0.7.1)
Provides-Extra: development
Requires-Dist: pip-tools (>6.5.1) ; extra == 'development'
Requires-Dist: black (>=22.1.0) ; extra == 'development'
Requires-Dist: bump2version (>=1.0.1) ; extra == 'development'
Requires-Dist: isort (>=5.10.1) ; extra == 'development'
Requires-Dist: tox (>=3.24.3) ; extra == 'development'
Requires-Dist: flake8 (>=4.0.1) ; extra == 'development'
Requires-Dist: flake8-mypy (>=17.8.0) ; extra == 'development'
Requires-Dist: mypy (>=0.931) ; extra == 'development'
Requires-Dist: pytest (>=7.0.1) ; extra == 'development'
Requires-Dist: pytest-cov (>=3.0.0) ; extra == 'development'
Provides-Extra: docs
Requires-Dist: sphinx (>=3.4.3) ; extra == 'docs'
Requires-Dist: ipykernel (>=5.4.3) ; extra == 'docs'
Requires-Dist: nbsphinx (>=0.8.1) ; extra == 'docs'
Requires-Dist: sphinx-rtd-theme (>=0.5.1) ; extra == 'docs'
Requires-Dist: pypandoc (>=1.5) ; extra == 'docs'
Requires-Dist: sphinx-autoapi (>=1.7.0) ; extra == 'docs'
